frenchlottery/__init__.py
frenchlottery/__main__.py
frenchlottery/euromillions_helper.py
frenchlottery/helper.py
frenchlottery/loto_helper.py
frenchlottery-0.3.0.dist-info/LICENSE.md
frenchlottery-0.3.0.dist-info/METADATA
frenchlottery-0.3.0.dist-info/WHEEL
frenchlottery-0.3.0.dist-info/RECORD
