Metadata-Version: 2.3
Name: frenchlottery
Version: 0.3.0
Summary: Get up-to-date lottery draws from FDJ
License: MIT
Author: Nicolas Voisin
Author-email: voisin.nicolas@gmail.com
Requires-Python: >=3.10
Classifier: Programming Language :: Python :: 3
Classifier: Operating System :: OS Independent
Requires-Dist: pandas (>=2.2.3,<3.0.0)
Requires-Dist: requests (>=2.32.3,<3.0.0)
Project-URL: Homepage, https://github.com/nick-voisin/frenchlottery
Project-URL: Issues, https://github.com/nick-voisin/frenchlottery/issues
